{
  "placeholderImages": [
    {
      "id": "up-seal",
      "description": "Seal of Uttar Pradesh government",
      "imageUrl": "/sealofup.jpg",
      "imageHint": "government seal"
    },
    {
      "id": "applicant-photo",
      "description": "Applicant's passport size photo",
      "imageUrl": "https://images.unsplash.com/photo-1521119989659-a83eee488004?crop=entropy&cs=tinysrgb&fit=max&fm=jpg&ixid=M3w3NDE5ODJ8MHwxfHNlYXJjaHw4fHxwZXJzb24lMjBwb3J0cmFpdHxlbnwwfHx8fDE3Njk0MTMyMzR8MA&ixlib=rb-4.1.0&q=80&w=1080",
      "imageHint": "person portrait"
    },
    {
      "id": "qr-code",
      "description": "QR code for certificate verification",
      "imageUrl": "",
      "imageHint": "qr code"
    },
    {
      "id": "gov-monogram",
      "description": "Government Monogram Watermark",
      "imageUrl": "/GOVERNMENT_MONOGRAM.gif",
      "imageHint": "book texture"
    }
  ]
}